fraclib/__init__.py
fraclib/fraccionario.py
fraclib/operaciones.py
fraclib/operaciones1.py
fraclib-2.1.dist-info/METADATA
fraclib-2.1.dist-info/WHEEL
fraclib-2.1.dist-info/top_level.txt
fraclib-2.1.dist-info/RECORD
