Metadata-Version: 2.1
Name: fraclib
Version: 2.1
Summary: Librería para trabajar con fracciones
Author: Rodrigo Enrique Guzman Roldan
Author-email: rodriguzrol1@gmail.com
